pikapy/__init__.py
pikapy/interpreter.py
pikapy/reader.py
pikapy/stack.py
pikapy/utils.py
pikapy-0.5.dist-info/LICENSE.txt
pikapy-0.5.dist-info/METADATA
pikapy-0.5.dist-info/WHEEL
pikapy-0.5.dist-info/top_level.txt
pikapy-0.5.dist-info/RECORD
